xmas.py
xmas-2022.1.dist-info/entry_points.txt
xmas-2022.1.dist-info/WHEEL
xmas-2022.1.dist-info/METADATA
xmas-2022.1.dist-info/RECORD
