Metadata-Version: 2.1
Name: xmas
Version: 2022.1
Summary: A cat, sitting on a wall, near a Xmas tree, is gazing starry picturesque night.
License: GPLv3+
Author-email: Nasy <nasyxx+git@gmail.com>
Requires-Python: >=3.8,<4.0
Classifier: License :: OSI Approved :: GNU General Public License v3 or later (GPLv3+)
Classifier: Programming Language :: Python :: 3
Classifier: Programming Language :: Python :: 3.10
Classifier: Programming Language :: Python :: 3.11
Classifier: Programming Language :: Python :: 3.8
Classifier: Programming Language :: Python :: 3.9
Project-URL: Repository, https://github.com/nasyxx/xmas.py
Project-URL: homepage, https://github.com/nasyxx/xmas.py
